domify/__about__.py
domify/__init__.py
domify/base_element.py
domify/exc.py
domify/html_elements.py
domify/py.typed
domify/validators.py
domify-0.4.7.dist-info/METADATA
domify-0.4.7.dist-info/WHEEL
domify-0.4.7.dist-info/licenses/LICENSE
domify-0.4.7.dist-info/RECORD
